[
    {
        "id": 1,
        "name": "Iphone X",
        "description": "Silver Iphone X With Airpods",
        "price": 700.0,
        "high": 1101.0,
        "link": "https://images.pexels.com/photos/788946/pexels-photo-788946.jpeg",
        "created_at": "2025-11-16 14:10:43",
        "last_bid_time": "2025-11-17 17:35:38"
    },
    {
        "id": 2,
        "name": "Mac",
        "description": "Minimalist Workspace with Apple Laptop and Keyboard",
        "price": 1500.0,
        "high": 1500.0,
        "link": "https://images.pexels.com/photos/34703569/pexels-photo-34703569.jpeg",
        "created_at": "2025-11-16 14:13:34"
    },
    {
        "id": 3,
        "name": "Watch",
        "description": "Round Michael Kors Chronograph Watch",
        "price": 100.0,
        "high": 700.0,
        "link": "https://images.pexels.com/photos/2783873/pexels-photo-2783873.jpeg",
        "created_at": "2025-11-16 14:18:42",
        "last_bid_time": "2025-11-17 15:50:31"
    },
    {
        "id": 4,
        "name": "house",
        "description": "Beige Bungalow House",
        "price": 20000.0,
        "high": 20000.1,
        "link": "https://images.pexels.com/photos/259588/pexels-photo-259588.jpeg",
        "created_at": "2025-11-17 11:15:18",
        "last_bid_time": "2025-11-17 11:19:35"
    },
    {
        "id": 5,
        "name": "TV",
        "description": "Black CRT TV",
        "price": 300.0,
        "high": 300.0,
        "link": "https://images.pexels.com/photos/2251206/pexels-photo-2251206.jpeg",
        "created_at": "2025-11-17 11:16:49"
    },
    {
        "id": 6,
        "name": "chess",
        "description": "Chess Pieces on Chess Board",
        "price": 100.0,
        "high": 100.0,
        "link": "https://images.pexels.com/photos/4973821/pexels-photo-4973821.jpeg",
        "created_at": "2025-11-17 11:27:50"
    },
    {
        "id": 13,
        "name": "headphones",
        "description": "Top View Photo of Black Wireless Headphones",
        "price": 70.0,
        "high": 71.0,
        "link": "https://images.pexels.com/photos/1649771/pexels-photo-1649771.jpeg",
        "created_at": "2025-11-17 16:47:52",
        "last_bid_time": "2025-11-18 11:10:50"
    },
    {
        "id": 14,
        "name": "headphones",
        "description": "Black Photo of Headphones with Purple Reflection\r\n",
        "price": 70.0,
        "high": 70.0,
        "link": "https://images.pexels.com/photos/10292805/pexels-photo-10292805.jpeg",
        "created_at": "2025-11-17 16:49:16"
    },
    {
        "id": 15,
        "name": "Land Rover",
        "description": "White Land Rover Range Rover Suv on Road\r\n",
        "price": 7000.0,
        "high": 7000.0,
        "link": "https://images.pexels.com/photos/116675/pexels-photo-116675.jpeg",
        "created_at": "2025-11-17 16:51:10"
    },
    {
        "id": 16,
        "name": "1212",
        "description": "1212",
        "price": 10.0,
        "high": 10.0,
        "link": "11",
        "created_at": "2025-11-18 11:42:16"
    },
    {
        "id": 17,
        "name": "111",
        "description": "111",
        "price": 10.0,
        "high": 10.0,
        "link": "111",
        "created_at": "2025-11-18 11:42:30"
    },
    {
        "id": 18,
        "name": "no",
        "description": "no ",
        "price": 100.0,
        "high": 100.0,
        "link": "no image",
        "created_at": "2025-11-18 12:20:58"
    }
]